README.rst
setup.cfg
setup.py
src/easy_sqlalchemy/__init__.py
src/easy_sqlalchemy/ext.py
src/easy_sqlalchemy/meta.py
src/easy_sqlalchemy.egg-info/PKG-INFO
src/easy_sqlalchemy.egg-info/SOURCES.txt
src/easy_sqlalchemy.egg-info/dependency_links.txt
src/easy_sqlalchemy.egg-info/not-zip-safe
src/easy_sqlalchemy.egg-info/requires.txt
src/easy_sqlalchemy.egg-info/top_level.txt
src/easy_sqlalchemy/types/__init__.py
src/easy_sqlalchemy/types/guid.py
src/easy_sqlalchemy/types/inet.py