Metadata-Version: 1.1
Name: easy-sqlalchemy
Version: 0.1.9
Summary: SQLAlchemy wrapper
Home-page: https://github.com/lxneng/easy_sqlalchemy
Author: Eric Lo
Author-email: lxneng@gmail.com
License: BSD
Platform: UNKNOWN
Classifier: Development Status :: 5 - Production/Stable
Classifier: Intended Audience :: Developers
Classifier: License :: OSI Approved :: BSD License
Classifier: Programming Language :: Python :: 2 :: Only
Classifier: Programming Language :: Python :: 2.6
Classifier: Programming Language :: Python :: 2.7
Classifier: Topic :: Database
Classifier: Topic :: Software Development :: Libraries :: Python Modules
